AppAuthN/CertificationReceiver.py
AppAuthN/CloseLoopCounter.py
AppAuthN/InferenceResult.py
AppAuthN/__init__.py
AppAuthN/config.json
AppAuthN-2.0.2.dist-info/LICENSE
AppAuthN-2.0.2.dist-info/METADATA
AppAuthN-2.0.2.dist-info/WHEEL
AppAuthN-2.0.2.dist-info/top_level.txt
AppAuthN-2.0.2.dist-info/RECORD
