Metadata-Version: 2.1
Name: AppAuthN
Version: 2.0.2
Requires-Python: >=3
License-File: LICENSE
Requires-Dist: requests
